pragma_prompt/__init__.py
pragma_prompt/exceptions.py
pragma_prompt/prompt_api.py
pragma_prompt/prompt_file_type.py
pragma_prompt/py.typed
pragma_prompt/render_engine.py
pragma_prompt/renderers/render_function.py
pragma_prompt/renderers/render_functions/block.py
pragma_prompt/renderers/render_functions/bullets.py
pragma_prompt/renderers/render_functions/code_block.py
pragma_prompt/renderers/render_functions/output_example.py
pragma_prompt/renderers/render_functions/separator.py
pragma_prompt/renderers/render_functions/shot.py
pragma_prompt/renderers/render_functions/table.py
pragma_prompt/renderers/render_functions/warning.py
pragma_prompt/renderers/render_plan.py
pragma_prompt/renderers/sections.py
pragma_prompt/renderers/types.py
pragma_prompt/renderers/utils.py
pragma_prompt/runtime_context.py
pragma_prompt-0.0.2.dist-info/LICENSE
pragma_prompt-0.0.2.dist-info/METADATA
pragma_prompt-0.0.2.dist-info/WHEEL
pragma_prompt-0.0.2.dist-info/RECORD
