Metadata-Version: 2.1
Name: pragma-prompt
Version: 0.0.2
Summary: A powerful toolkit for building, managing, and composing hierarchical prompts as code.
Home-page: https://github.com/DavidTokar12/PragmaPrompt
License: MIT
Keywords: prompt,llm,prompt-engineering,ai,openai,claude,anthropic,hierarchical prompts,prompt management
Author: David Tokar
Author-email: 1413david@gmail.com
Requires-Python: >=3.10,<4.0
Classifier: Development Status :: 3 - Alpha
Classifier: Intended Audience :: Developers
Classifier: License :: OSI Approved :: MIT License
Classifier: Programming Language :: Python :: 3
Classifier: Programming Language :: Python :: 3.10
Classifier: Programming Language :: Python :: 3.11
Classifier: Programming Language :: Python :: 3.12
Classifier: Topic :: Scientific/Engineering :: Artificial Intelligence
Classifier: Topic :: Software Development :: Libraries :: Python Modules
Classifier: Typing :: Typed
Requires-Dist: prettytable (>=3.16.0,<4.0.0)
Requires-Dist: pydantic (>=2.11.7,<3.0.0)
Project-URL: Repository, https://github.com/DavidTokar12/PragmaPrompt
